lein_vector/__init__.py
lein_vector/api/__init__.py
lein_vector/api/facade.py
lein_vector/bases/__init__.py
lein_vector/bases/embeding_provider_abc.py
lein_vector/bases/memory_manager_abc.py
lein_vector/memory_manager_qdrant.py
lein_vector/memory_manager_ram.py
lein_vector/qdrant_adapter.py
lein_vector/schemas/__init__.py
lein_vector/schemas/chunk.py
lein_vector/sentence_transformer.py
lein_vector/short_term.py
lein_vector-0.1.0.6.dist-info/METADATA
lein_vector-0.1.0.6.dist-info/WHEEL
lein_vector-0.1.0.6.dist-info/RECORD
