Metadata-Version: 2.3
Name: lein_vector
Version: 0.1.0.6
Summary: 
Author: p00ler
Author-email: liveitspain@gmail.com
Requires-Python: >=3.11
Classifier: Programming Language :: Python :: 3
Classifier: Programming Language :: Python :: 3.11
Classifier: Programming Language :: Python :: 3.12
Classifier: Programming Language :: Python :: 3.13
Requires-Dist: aiohttp (>=3.12.13,<4.0.0)
Requires-Dist: google-genai[aiohttp] (>=1.21.1,<2.0.0)
Requires-Dist: qdrant-client (>=1.14.3,<2.0.0)
